{
  "openapi": "3.1.0",
  "info": {
    "title": "git-mcp-server-web",
    "description": "Standalone SPA delivery server for git-mcp-server.",
    "version": "0.1.0"
  },
  "paths": {
    "/health": {
      "get": {
        "tags": [
          "health"
        ],
        "summary": "Health",
        "description": "Liveness probe with compatibility checks payload when configured.",
        "operationId": "health_health_get",
        "responses": {
          "200": {
            "description": "Successful Response",
            "content": {
              "application/json": {
                "schema": {
                  "additionalProperties": true,
                  "type": "object",
                  "title": "Response Health Health Get"
                }
              }
            }
          }
        }
      }
    },
    "/ready": {
      "get": {
        "tags": [
          "health"
        ],
        "summary": "Ready",
        "description": "Readiness probe \u2014 returns OK only when all critical dependencies are up.",
        "operationId": "ready_ready_get",
        "responses": {
          "200": {
            "description": "Successful Response",
            "content": {
              "application/json": {
                "schema": {
                  "additionalProperties": true,
                  "type": "object",
                  "title": "Response Ready Ready Get"
                }
              }
            }
          }
        }
      }
    },
    "/live": {
      "get": {
        "tags": [
          "health"
        ],
        "summary": "Live",
        "description": "Liveness alias \u2014 same as /health.",
        "operationId": "live_live_get",
        "responses": {
          "200": {
            "description": "Successful Response",
            "content": {
              "application/json": {
                "schema": {
                  "additionalProperties": true,
                  "type": "object",
                  "title": "Response Live Live Get"
                }
              }
            }
          }
        }
      }
    },
    "/api/v1/version": {
      "get": {
        "tags": [
          "system"
        ],
        "summary": "Api Version",
        "description": "Return the API version information.",
        "operationId": "api_version_api_v1_version_get",
        "responses": {
          "200": {
            "description": "Successful Response",
            "content": {
              "application/json": {
                "schema": {
                  "additionalProperties": true,
                  "type": "object",
                  "title": "Response Api Version Api V1 Version Get"
                }
              }
            }
          }
        }
      }
    },
    "/auth/login": {
      "post": {
        "summary": "Auth Login",
        "description": "Validate username/password and create session.",
        "operationId": "auth_login_auth_login_post",
        "responses": {
          "200": {
            "description": "Successful Response",
            "content": {
              "application/json": {
                "schema": {}
              }
            }
          }
        }
      }
    },
    "/auth/me": {
      "get": {
        "summary": "Auth Me",
        "description": "Return current session user.",
        "operationId": "auth_me_auth_me_get",
        "responses": {
          "200": {
            "description": "Successful Response",
            "content": {
              "application/json": {
                "schema": {}
              }
            }
          }
        }
      }
    },
    "/auth/logout": {
      "post": {
        "summary": "Auth Logout",
        "description": "Clear session.",
        "operationId": "auth_logout_auth_logout_post",
        "responses": {
          "200": {
            "description": "Successful Response",
            "content": {
              "application/json": {
                "schema": {}
              }
            }
          }
        }
      }
    },
    "/status": {
      "get": {
        "summary": "Ui Status",
        "description": "Return the unauthenticated UI status payload used by the SPA dashboard.",
        "operationId": "ui_status_status_get",
        "responses": {
          "200": {
            "description": "Successful Response",
            "content": {
              "application/json": {
                "schema": {}
              }
            }
          }
        }
      }
    },
    "/api/v1/{path}": {
      "get": {
        "summary": "Proxy Api",
        "description": "Proxy cookie-authenticated UI API calls to the backend API server.",
        "operationId": "proxy_api_api_v1__path__get",
        "parameters": [
          {
            "name": "path",
            "in": "path",
            "required": true,
            "schema": {
              "type": "string",
              "title": "Path"
            }
          }
        ],
        "responses": {
          "200": {
            "description": "Successful Response",
            "content": {
              "application/json": {
                "schema": {}
              }
            }
          },
          "422": {
            "description": "Validation Error",
            "content": {
              "application/json": {
                "schema": {
                  "$ref": "#/components/schemas/HTTPValidationError"
                }
              }
            }
          }
        }
      },
      "patch": {
        "summary": "Proxy Api",
        "description": "Proxy cookie-authenticated UI API calls to the backend API server.",
        "operationId": "proxy_api_api_v1__path__get",
        "parameters": [
          {
            "name": "path",
            "in": "path",
            "required": true,
            "schema": {
              "type": "string",
              "title": "Path"
            }
          }
        ],
        "responses": {
          "200": {
            "description": "Successful Response",
            "content": {
              "application/json": {
                "schema": {}
              }
            }
          },
          "422": {
            "description": "Validation Error",
            "content": {
              "application/json": {
                "schema": {
                  "$ref": "#/components/schemas/HTTPValidationError"
                }
              }
            }
          }
        }
      },
      "post": {
        "summary": "Proxy Api",
        "description": "Proxy cookie-authenticated UI API calls to the backend API server.",
        "operationId": "proxy_api_api_v1__path__get",
        "parameters": [
          {
            "name": "path",
            "in": "path",
            "required": true,
            "schema": {
              "type": "string",
              "title": "Path"
            }
          }
        ],
        "responses": {
          "200": {
            "description": "Successful Response",
            "content": {
              "application/json": {
                "schema": {}
              }
            }
          },
          "422": {
            "description": "Validation Error",
            "content": {
              "application/json": {
                "schema": {
                  "$ref": "#/components/schemas/HTTPValidationError"
                }
              }
            }
          }
        }
      },
      "put": {
        "summary": "Proxy Api",
        "description": "Proxy cookie-authenticated UI API calls to the backend API server.",
        "operationId": "proxy_api_api_v1__path__get",
        "parameters": [
          {
            "name": "path",
            "in": "path",
            "required": true,
            "schema": {
              "type": "string",
              "title": "Path"
            }
          }
        ],
        "responses": {
          "200": {
            "description": "Successful Response",
            "content": {
              "application/json": {
                "schema": {}
              }
            }
          },
          "422": {
            "description": "Validation Error",
            "content": {
              "application/json": {
                "schema": {
                  "$ref": "#/components/schemas/HTTPValidationError"
                }
              }
            }
          }
        }
      },
      "delete": {
        "summary": "Proxy Api",
        "description": "Proxy cookie-authenticated UI API calls to the backend API server.",
        "operationId": "proxy_api_api_v1__path__get",
        "parameters": [
          {
            "name": "path",
            "in": "path",
            "required": true,
            "schema": {
              "type": "string",
              "title": "Path"
            }
          }
        ],
        "responses": {
          "200": {
            "description": "Successful Response",
            "content": {
              "application/json": {
                "schema": {}
              }
            }
          },
          "422": {
            "description": "Validation Error",
            "content": {
              "application/json": {
                "schema": {
                  "$ref": "#/components/schemas/HTTPValidationError"
                }
              }
            }
          }
        }
      }
    },
    "/api/v1": {
      "get": {
        "summary": "Proxy Api Root",
        "description": "Proxy cookie-authenticated UI API root calls to the backend API server.",
        "operationId": "proxy_api_root_api_v1_get",
        "responses": {
          "200": {
            "description": "Successful Response",
            "content": {
              "application/json": {
                "schema": {}
              }
            }
          }
        }
      },
      "put": {
        "summary": "Proxy Api Root",
        "description": "Proxy cookie-authenticated UI API root calls to the backend API server.",
        "operationId": "proxy_api_root_api_v1_get",
        "responses": {
          "200": {
            "description": "Successful Response",
            "content": {
              "application/json": {
                "schema": {}
              }
            }
          }
        }
      },
      "post": {
        "summary": "Proxy Api Root",
        "description": "Proxy cookie-authenticated UI API root calls to the backend API server.",
        "operationId": "proxy_api_root_api_v1_get",
        "responses": {
          "200": {
            "description": "Successful Response",
            "content": {
              "application/json": {
                "schema": {}
              }
            }
          }
        }
      },
      "delete": {
        "summary": "Proxy Api Root",
        "description": "Proxy cookie-authenticated UI API root calls to the backend API server.",
        "operationId": "proxy_api_root_api_v1_get",
        "responses": {
          "200": {
            "description": "Successful Response",
            "content": {
              "application/json": {
                "schema": {}
              }
            }
          }
        }
      },
      "patch": {
        "summary": "Proxy Api Root",
        "description": "Proxy cookie-authenticated UI API root calls to the backend API server.",
        "operationId": "proxy_api_root_api_v1_get",
        "responses": {
          "200": {
            "description": "Successful Response",
            "content": {
              "application/json": {
                "schema": {}
              }
            }
          }
        }
      }
    },
    "/git-mcp/{path}": {
      "get": {
        "summary": "Proxy Mcp",
        "description": "Proxy cookie-authenticated UI MCP calls to the backend MCP server.",
        "operationId": "proxy_mcp_git_mcp__path__get",
        "parameters": [
          {
            "name": "path",
            "in": "path",
            "required": true,
            "schema": {
              "type": "string",
              "title": "Path"
            }
          }
        ],
        "responses": {
          "200": {
            "description": "Successful Response",
            "content": {
              "application/json": {
                "schema": {}
              }
            }
          },
          "422": {
            "description": "Validation Error",
            "content": {
              "application/json": {
                "schema": {
                  "$ref": "#/components/schemas/HTTPValidationError"
                }
              }
            }
          }
        }
      },
      "patch": {
        "summary": "Proxy Mcp",
        "description": "Proxy cookie-authenticated UI MCP calls to the backend MCP server.",
        "operationId": "proxy_mcp_git_mcp__path__get",
        "parameters": [
          {
            "name": "path",
            "in": "path",
            "required": true,
            "schema": {
              "type": "string",
              "title": "Path"
            }
          }
        ],
        "responses": {
          "200": {
            "description": "Successful Response",
            "content": {
              "application/json": {
                "schema": {}
              }
            }
          },
          "422": {
            "description": "Validation Error",
            "content": {
              "application/json": {
                "schema": {
                  "$ref": "#/components/schemas/HTTPValidationError"
                }
              }
            }
          }
        }
      },
      "post": {
        "summary": "Proxy Mcp",
        "description": "Proxy cookie-authenticated UI MCP calls to the backend MCP server.",
        "operationId": "proxy_mcp_git_mcp__path__get",
        "parameters": [
          {
            "name": "path",
            "in": "path",
            "required": true,
            "schema": {
              "type": "string",
              "title": "Path"
            }
          }
        ],
        "responses": {
          "200": {
            "description": "Successful Response",
            "content": {
              "application/json": {
                "schema": {}
              }
            }
          },
          "422": {
            "description": "Validation Error",
            "content": {
              "application/json": {
                "schema": {
                  "$ref": "#/components/schemas/HTTPValidationError"
                }
              }
            }
          }
        }
      },
      "put": {
        "summary": "Proxy Mcp",
        "description": "Proxy cookie-authenticated UI MCP calls to the backend MCP server.",
        "operationId": "proxy_mcp_git_mcp__path__get",
        "parameters": [
          {
            "name": "path",
            "in": "path",
            "required": true,
            "schema": {
              "type": "string",
              "title": "Path"
            }
          }
        ],
        "responses": {
          "200": {
            "description": "Successful Response",
            "content": {
              "application/json": {
                "schema": {}
              }
            }
          },
          "422": {
            "description": "Validation Error",
            "content": {
              "application/json": {
                "schema": {
                  "$ref": "#/components/schemas/HTTPValidationError"
                }
              }
            }
          }
        }
      },
      "delete": {
        "summary": "Proxy Mcp",
        "description": "Proxy cookie-authenticated UI MCP calls to the backend MCP server.",
        "operationId": "proxy_mcp_git_mcp__path__get",
        "parameters": [
          {
            "name": "path",
            "in": "path",
            "required": true,
            "schema": {
              "type": "string",
              "title": "Path"
            }
          }
        ],
        "responses": {
          "200": {
            "description": "Successful Response",
            "content": {
              "application/json": {
                "schema": {}
              }
            }
          },
          "422": {
            "description": "Validation Error",
            "content": {
              "application/json": {
                "schema": {
                  "$ref": "#/components/schemas/HTTPValidationError"
                }
              }
            }
          }
        }
      }
    },
    "/git-mcp": {
      "get": {
        "summary": "Proxy Mcp Root",
        "description": "Proxy cookie-authenticated UI MCP root calls to the backend MCP server.",
        "operationId": "proxy_mcp_root_git_mcp_get",
        "responses": {
          "200": {
            "description": "Successful Response",
            "content": {
              "application/json": {
                "schema": {}
              }
            }
          }
        }
      },
      "put": {
        "summary": "Proxy Mcp Root",
        "description": "Proxy cookie-authenticated UI MCP root calls to the backend MCP server.",
        "operationId": "proxy_mcp_root_git_mcp_get",
        "responses": {
          "200": {
            "description": "Successful Response",
            "content": {
              "application/json": {
                "schema": {}
              }
            }
          }
        }
      },
      "post": {
        "summary": "Proxy Mcp Root",
        "description": "Proxy cookie-authenticated UI MCP root calls to the backend MCP server.",
        "operationId": "proxy_mcp_root_git_mcp_get",
        "responses": {
          "200": {
            "description": "Successful Response",
            "content": {
              "application/json": {
                "schema": {}
              }
            }
          }
        }
      },
      "delete": {
        "summary": "Proxy Mcp Root",
        "description": "Proxy cookie-authenticated UI MCP root calls to the backend MCP server.",
        "operationId": "proxy_mcp_root_git_mcp_get",
        "responses": {
          "200": {
            "description": "Successful Response",
            "content": {
              "application/json": {
                "schema": {}
              }
            }
          }
        }
      },
      "patch": {
        "summary": "Proxy Mcp Root",
        "description": "Proxy cookie-authenticated UI MCP root calls to the backend MCP server.",
        "operationId": "proxy_mcp_root_git_mcp_get",
        "responses": {
          "200": {
            "description": "Successful Response",
            "content": {
              "application/json": {
                "schema": {}
              }
            }
          }
        }
      }
    },
    "/a2a/{path}": {
      "get": {
        "summary": "Proxy A2A",
        "description": "Proxy cookie-authenticated UI A2A HTTP calls to the backend A2A server.",
        "operationId": "proxy_a2a_a2a__path__get",
        "parameters": [
          {
            "name": "path",
            "in": "path",
            "required": true,
            "schema": {
              "type": "string",
              "title": "Path"
            }
          }
        ],
        "responses": {
          "200": {
            "description": "Successful Response",
            "content": {
              "application/json": {
                "schema": {}
              }
            }
          },
          "422": {
            "description": "Validation Error",
            "content": {
              "application/json": {
                "schema": {
                  "$ref": "#/components/schemas/HTTPValidationError"
                }
              }
            }
          }
        }
      },
      "patch": {
        "summary": "Proxy A2A",
        "description": "Proxy cookie-authenticated UI A2A HTTP calls to the backend A2A server.",
        "operationId": "proxy_a2a_a2a__path__get",
        "parameters": [
          {
            "name": "path",
            "in": "path",
            "required": true,
            "schema": {
              "type": "string",
              "title": "Path"
            }
          }
        ],
        "responses": {
          "200": {
            "description": "Successful Response",
            "content": {
              "application/json": {
                "schema": {}
              }
            }
          },
          "422": {
            "description": "Validation Error",
            "content": {
              "application/json": {
                "schema": {
                  "$ref": "#/components/schemas/HTTPValidationError"
                }
              }
            }
          }
        }
      },
      "post": {
        "summary": "Proxy A2A",
        "description": "Proxy cookie-authenticated UI A2A HTTP calls to the backend A2A server.",
        "operationId": "proxy_a2a_a2a__path__get",
        "parameters": [
          {
            "name": "path",
            "in": "path",
            "required": true,
            "schema": {
              "type": "string",
              "title": "Path"
            }
          }
        ],
        "responses": {
          "200": {
            "description": "Successful Response",
            "content": {
              "application/json": {
                "schema": {}
              }
            }
          },
          "422": {
            "description": "Validation Error",
            "content": {
              "application/json": {
                "schema": {
                  "$ref": "#/components/schemas/HTTPValidationError"
                }
              }
            }
          }
        }
      },
      "put": {
        "summary": "Proxy A2A",
        "description": "Proxy cookie-authenticated UI A2A HTTP calls to the backend A2A server.",
        "operationId": "proxy_a2a_a2a__path__get",
        "parameters": [
          {
            "name": "path",
            "in": "path",
            "required": true,
            "schema": {
              "type": "string",
              "title": "Path"
            }
          }
        ],
        "responses": {
          "200": {
            "description": "Successful Response",
            "content": {
              "application/json": {
                "schema": {}
              }
            }
          },
          "422": {
            "description": "Validation Error",
            "content": {
              "application/json": {
                "schema": {
                  "$ref": "#/components/schemas/HTTPValidationError"
                }
              }
            }
          }
        }
      },
      "delete": {
        "summary": "Proxy A2A",
        "description": "Proxy cookie-authenticated UI A2A HTTP calls to the backend A2A server.",
        "operationId": "proxy_a2a_a2a__path__get",
        "parameters": [
          {
            "name": "path",
            "in": "path",
            "required": true,
            "schema": {
              "type": "string",
              "title": "Path"
            }
          }
        ],
        "responses": {
          "200": {
            "description": "Successful Response",
            "content": {
              "application/json": {
                "schema": {}
              }
            }
          },
          "422": {
            "description": "Validation Error",
            "content": {
              "application/json": {
                "schema": {
                  "$ref": "#/components/schemas/HTTPValidationError"
                }
              }
            }
          }
        }
      }
    },
    "/a2a": {
      "get": {
        "summary": "Proxy A2A Root",
        "description": "Proxy cookie-authenticated UI A2A root calls to the backend A2A server.",
        "operationId": "proxy_a2a_root_a2a_get",
        "responses": {
          "200": {
            "description": "Successful Response",
            "content": {
              "application/json": {
                "schema": {}
              }
            }
          }
        }
      },
      "put": {
        "summary": "Proxy A2A Root",
        "description": "Proxy cookie-authenticated UI A2A root calls to the backend A2A server.",
        "operationId": "proxy_a2a_root_a2a_get",
        "responses": {
          "200": {
            "description": "Successful Response",
            "content": {
              "application/json": {
                "schema": {}
              }
            }
          }
        }
      },
      "post": {
        "summary": "Proxy A2A Root",
        "description": "Proxy cookie-authenticated UI A2A root calls to the backend A2A server.",
        "operationId": "proxy_a2a_root_a2a_get",
        "responses": {
          "200": {
            "description": "Successful Response",
            "content": {
              "application/json": {
                "schema": {}
              }
            }
          }
        }
      },
      "delete": {
        "summary": "Proxy A2A Root",
        "description": "Proxy cookie-authenticated UI A2A root calls to the backend A2A server.",
        "operationId": "proxy_a2a_root_a2a_get",
        "responses": {
          "200": {
            "description": "Successful Response",
            "content": {
              "application/json": {
                "schema": {}
              }
            }
          }
        }
      },
      "patch": {
        "summary": "Proxy A2A Root",
        "description": "Proxy cookie-authenticated UI A2A root calls to the backend A2A server.",
        "operationId": "proxy_a2a_root_a2a_get",
        "responses": {
          "200": {
            "description": "Successful Response",
            "content": {
              "application/json": {
                "schema": {}
              }
            }
          }
        }
      }
    },
    "/web/api/{path}": {
      "get": {
        "summary": "Proxy Web Api",
        "description": "Proxy compatibility cleanup routes under /web/api/* to JSON API surfaces.",
        "operationId": "proxy_web_api_web_api__path__get",
        "parameters": [
          {
            "name": "path",
            "in": "path",
            "required": true,
            "schema": {
              "type": "string",
              "title": "Path"
            }
          }
        ],
        "responses": {
          "200": {
            "description": "Successful Response",
            "content": {
              "application/json": {
                "schema": {}
              }
            }
          },
          "422": {
            "description": "Validation Error",
            "content": {
              "application/json": {
                "schema": {
                  "$ref": "#/components/schemas/HTTPValidationError"
                }
              }
            }
          }
        }
      },
      "patch": {
        "summary": "Proxy Web Api",
        "description": "Proxy compatibility cleanup routes under /web/api/* to JSON API surfaces.",
        "operationId": "proxy_web_api_web_api__path__get",
        "parameters": [
          {
            "name": "path",
            "in": "path",
            "required": true,
            "schema": {
              "type": "string",
              "title": "Path"
            }
          }
        ],
        "responses": {
          "200": {
            "description": "Successful Response",
            "content": {
              "application/json": {
                "schema": {}
              }
            }
          },
          "422": {
            "description": "Validation Error",
            "content": {
              "application/json": {
                "schema": {
                  "$ref": "#/components/schemas/HTTPValidationError"
                }
              }
            }
          }
        }
      },
      "post": {
        "summary": "Proxy Web Api",
        "description": "Proxy compatibility cleanup routes under /web/api/* to JSON API surfaces.",
        "operationId": "proxy_web_api_web_api__path__get",
        "parameters": [
          {
            "name": "path",
            "in": "path",
            "required": true,
            "schema": {
              "type": "string",
              "title": "Path"
            }
          }
        ],
        "responses": {
          "200": {
            "description": "Successful Response",
            "content": {
              "application/json": {
                "schema": {}
              }
            }
          },
          "422": {
            "description": "Validation Error",
            "content": {
              "application/json": {
                "schema": {
                  "$ref": "#/components/schemas/HTTPValidationError"
                }
              }
            }
          }
        }
      },
      "put": {
        "summary": "Proxy Web Api",
        "description": "Proxy compatibility cleanup routes under /web/api/* to JSON API surfaces.",
        "operationId": "proxy_web_api_web_api__path__get",
        "parameters": [
          {
            "name": "path",
            "in": "path",
            "required": true,
            "schema": {
              "type": "string",
              "title": "Path"
            }
          }
        ],
        "responses": {
          "200": {
            "description": "Successful Response",
            "content": {
              "application/json": {
                "schema": {}
              }
            }
          },
          "422": {
            "description": "Validation Error",
            "content": {
              "application/json": {
                "schema": {
                  "$ref": "#/components/schemas/HTTPValidationError"
                }
              }
            }
          }
        }
      },
      "delete": {
        "summary": "Proxy Web Api",
        "description": "Proxy compatibility cleanup routes under /web/api/* to JSON API surfaces.",
        "operationId": "proxy_web_api_web_api__path__get",
        "parameters": [
          {
            "name": "path",
            "in": "path",
            "required": true,
            "schema": {
              "type": "string",
              "title": "Path"
            }
          }
        ],
        "responses": {
          "200": {
            "description": "Successful Response",
            "content": {
              "application/json": {
                "schema": {}
              }
            }
          },
          "422": {
            "description": "Validation Error",
            "content": {
              "application/json": {
                "schema": {
                  "$ref": "#/components/schemas/HTTPValidationError"
                }
              }
            }
          }
        }
      }
    },
    "/web/api": {
      "get": {
        "summary": "Proxy Web Api Root",
        "description": "Reject unsupported bare compatibility root requests deterministically.",
        "operationId": "proxy_web_api_root_web_api_get",
        "responses": {
          "200": {
            "description": "Successful Response",
            "content": {
              "application/json": {
                "schema": {}
              }
            }
          }
        }
      },
      "put": {
        "summary": "Proxy Web Api Root",
        "description": "Reject unsupported bare compatibility root requests deterministically.",
        "operationId": "proxy_web_api_root_web_api_get",
        "responses": {
          "200": {
            "description": "Successful Response",
            "content": {
              "application/json": {
                "schema": {}
              }
            }
          }
        }
      },
      "post": {
        "summary": "Proxy Web Api Root",
        "description": "Reject unsupported bare compatibility root requests deterministically.",
        "operationId": "proxy_web_api_root_web_api_get",
        "responses": {
          "200": {
            "description": "Successful Response",
            "content": {
              "application/json": {
                "schema": {}
              }
            }
          }
        }
      },
      "delete": {
        "summary": "Proxy Web Api Root",
        "description": "Reject unsupported bare compatibility root requests deterministically.",
        "operationId": "proxy_web_api_root_web_api_get",
        "responses": {
          "200": {
            "description": "Successful Response",
            "content": {
              "application/json": {
                "schema": {}
              }
            }
          }
        }
      },
      "patch": {
        "summary": "Proxy Web Api Root",
        "description": "Reject unsupported bare compatibility root requests deterministically.",
        "operationId": "proxy_web_api_root_web_api_get",
        "responses": {
          "200": {
            "description": "Successful Response",
            "content": {
              "application/json": {
                "schema": {}
              }
            }
          }
        }
      }
    },
    "/runtime-config.js": {
      "get": {
        "summary": "Runtime Config",
        "description": "Requirements: FR-16, FR-17.\n\nUses JavaScript expressions for URL values so the browser resolves\nthe correct protocol behind a reverse proxy (Traefik / HTTPS).",
        "operationId": "runtime_config_runtime_config_js_get",
        "responses": {
          "200": {
            "description": "Successful Response"
          }
        }
      }
    },
    "/": {
      "get": {
        "summary": "Spa Root",
        "description": "Requirements: FR-16, FR-17.",
        "operationId": "spa_root__get",
        "responses": {
          "200": {
            "description": "Successful Response"
          }
        }
      }
    },
    "/a2a-console": {
      "get": {
        "summary": "Spa Known Deep Links",
        "description": "Serve SPA routes that overlap API/MCP naming but are UI pages.",
        "operationId": "spa_known_deep_links_a2a_console_get",
        "responses": {
          "200": {
            "description": "Successful Response"
          }
        }
      }
    },
    "/mcp-console": {
      "get": {
        "summary": "Spa Known Deep Links",
        "description": "Serve SPA routes that overlap API/MCP naming but are UI pages.",
        "operationId": "spa_known_deep_links_mcp_console_get",
        "responses": {
          "200": {
            "description": "Successful Response"
          }
        }
      }
    },
    "/api-docs": {
      "get": {
        "summary": "Spa Known Deep Links",
        "description": "Serve SPA routes that overlap API/MCP naming but are UI pages.",
        "operationId": "spa_known_deep_links_api_docs_get",
        "responses": {
          "200": {
            "description": "Successful Response"
          }
        }
      }
    },
    "/{path}": {
      "get": {
        "summary": "Spa Fallback",
        "description": "Requirements: FR-16, FR-17.",
        "operationId": "spa_fallback__path__get",
        "parameters": [
          {
            "name": "path",
            "in": "path",
            "required": true,
            "schema": {
              "type": "string",
              "title": "Path"
            }
          }
        ],
        "responses": {
          "200": {
            "description": "Successful Response"
          },
          "422": {
            "description": "Validation Error",
            "content": {
              "application/json": {
                "schema": {
                  "$ref": "#/components/schemas/HTTPValidationError"
                }
              }
            }
          }
        }
      }
    }
  },
  "components": {
    "schemas": {
      "HTTPValidationError": {
        "properties": {
          "detail": {
            "items": {
              "$ref": "#/components/schemas/ValidationError"
            },
            "type": "array",
            "title": "Detail"
          }
        },
        "type": "object",
        "title": "HTTPValidationError"
      },
      "ValidationError": {
        "properties": {
          "loc": {
            "items": {
              "anyOf": [
                {
                  "type": "string"
                },
                {
                  "type": "integer"
                }
              ]
            },
            "type": "array",
            "title": "Location"
          },
          "msg": {
            "type": "string",
            "title": "Message"
          },
          "type": {
            "type": "string",
            "title": "Error Type"
          },
          "input": {
            "title": "Input"
          },
          "ctx": {
            "type": "object",
            "title": "Context"
          }
        },
        "type": "object",
        "required": [
          "loc",
          "msg",
          "type"
        ],
        "title": "ValidationError"
      }
    }
  }
}